odoo/addons/account_invoice_warn_message/README.rst
odoo/addons/account_invoice_warn_message/__init__.py
odoo/addons/account_invoice_warn_message/__manifest__.py
odoo/addons/account_invoice_warn_message/i18n/account_invoice_warn_message.pot
odoo/addons/account_invoice_warn_message/i18n/es.po
odoo/addons/account_invoice_warn_message/i18n/it.po
odoo/addons/account_invoice_warn_message/models/__init__.py
odoo/addons/account_invoice_warn_message/models/account_move.py
odoo/addons/account_invoice_warn_message/readme/CONTRIBUTORS.rst
odoo/addons/account_invoice_warn_message/readme/DESCRIPTION.rst
odoo/addons/account_invoice_warn_message/static/description/icon.png
odoo/addons/account_invoice_warn_message/static/description/index.html
odoo/addons/account_invoice_warn_message/tests/__init__.py
odoo/addons/account_invoice_warn_message/tests/test_account_invoice_warn_message.py
odoo/addons/account_invoice_warn_message/views/account_move_views.xml
odoo14_addon_account_invoice_warn_message-14.0.1.0.1.dev3.dist-info/METADATA
odoo14_addon_account_invoice_warn_message-14.0.1.0.1.dev3.dist-info/WHEEL
odoo14_addon_account_invoice_warn_message-14.0.1.0.1.dev3.dist-info/top_level.txt
odoo14_addon_account_invoice_warn_message-14.0.1.0.1.dev3.dist-info/RECORD
